EffectiveJava3rdZhongwenban/README.md
EffectiveJava3rdZhongwenban/__init__.py
EffectiveJava3rdZhongwenban/__main__.py
EffectiveJava3rdZhongwenban/file.epub
EffectiveJava3rdZhongwenban/index.html
EffectiveJava3rdZhongwenban/css/__init__.py
EffectiveJava3rdZhongwenban/css/annotations.css
EffectiveJava3rdZhongwenban/css/main.css
EffectiveJava3rdZhongwenban/css/normalize.css
EffectiveJava3rdZhongwenban/css/popup.css
EffectiveJava3rdZhongwenban/font/__init__.py
EffectiveJava3rdZhongwenban/font/fontello.eot
EffectiveJava3rdZhongwenban/font/fontello.svg
EffectiveJava3rdZhongwenban/font/fontello.ttf
EffectiveJava3rdZhongwenban/font/fontello.woff
EffectiveJava3rdZhongwenban/img/__init__.py
EffectiveJava3rdZhongwenban/img/annotator-glyph-sprite.png
EffectiveJava3rdZhongwenban/img/annotator-icon-sprite.png
EffectiveJava3rdZhongwenban/img/apple-touch-icon.png
EffectiveJava3rdZhongwenban/img/cancelfullscreen.png
EffectiveJava3rdZhongwenban/img/close.png
EffectiveJava3rdZhongwenban/img/fullscreen.png
EffectiveJava3rdZhongwenban/img/loader.gif
EffectiveJava3rdZhongwenban/img/menu-icon.png
EffectiveJava3rdZhongwenban/img/save.png
EffectiveJava3rdZhongwenban/img/saved.png
EffectiveJava3rdZhongwenban/img/settings-s.png
EffectiveJava3rdZhongwenban/img/settings.png
EffectiveJava3rdZhongwenban/img/star.png
EffectiveJava3rdZhongwenban/js/__init__.py
EffectiveJava3rdZhongwenban/js/epub.js
EffectiveJava3rdZhongwenban/js/epub.min.js
EffectiveJava3rdZhongwenban/js/epub.min.map
EffectiveJava3rdZhongwenban/js/hooks.min.js
EffectiveJava3rdZhongwenban/js/hooks.min.map
EffectiveJava3rdZhongwenban/js/reader.js
EffectiveJava3rdZhongwenban/js/reader.js.map
EffectiveJava3rdZhongwenban/js/reader.min.js
EffectiveJava3rdZhongwenban/js/reader.min.map
EffectiveJava3rdZhongwenban/js/hooks/__init__.py
EffectiveJava3rdZhongwenban/js/hooks/extensions/__init__.py
EffectiveJava3rdZhongwenban/js/hooks/extensions/highlight.js
EffectiveJava3rdZhongwenban/js/libs/__init__.py
effective_java_3rd_zhongwenban-2024.3.4.0.dist-info/METADATA
effective_java_3rd_zhongwenban-2024.3.4.0.dist-info/WHEEL
effective_java_3rd_zhongwenban-2024.3.4.0.dist-info/entry_points.txt
effective_java_3rd_zhongwenban-2024.3.4.0.dist-info/top_level.txt
effective_java_3rd_zhongwenban-2024.3.4.0.dist-info/RECORD
